{
  "version": "2.0",
  "schema_ref": "https://darwin-public.s3.eu-west-1.amazonaws.com/darwin_json/2.0/schema.json",
  "item": {
    "name": "DJI_20221221095842_0057_Z.JPG",
    "path": "/",
    "source_info": {
      "dataset": {
        "name": "Winter 22 - Zoom Camera Images",
        "slug": "winter-22-zoom-camera-images",
        "dataset_management_url": "https://darwin.v7labs.com/datasets/614552/dataset-management"
      },
      "item_id": "018624b7-57e2-c13c-9c81-330219553652",
      "team": {
        "name": "MAV Dronework",
        "slug": "mav-dronework"
      },
      "workview_url": "https://darwin.v7labs.com/workview?dataset=614552&item=018624b7-57e2-c13c-9c81-330219553652"
    },
    "slots": [
      {
        "type": "image",
        "slot_name": "0",
        "width": 5184,
        "height": 2916,
        "thumbnail_url": "https://darwin.v7labs.com/api/v2/teams/mav-dronework/files/0d02a3f0-3fbd-44a9-b637-61c3b40de0cc/thumbnail",
        "source_files": [
          {
            "file_name": "DJI_20221221095842_0057_Z.JPG",
            "url": "https://darwin.v7labs.com/api/v2/teams/mav-dronework/uploads/6769c7c2-a8e4-4dd9-a79a-5ce2abcf8dc6"
          }
        ]
      }
    ]
  },
  "annotations": [
    {
      "bounding_box": {
        "h": 369.23,
        "w": 245.92999999999995,
        "x": 780.4,
        "y": 1659.08
      },
      "id": "39ce885b-4393-4dc2-87a6-1f07e2225572",
      "name": "GWTE",
      "polygon": {
        "paths": [
          [
            {
              "x": 822.17,
              "y": 1665.82
            },
            {
              "x": 813.41,
              "y": 1694.79
            },
            {
              "x": 812.74,
              "y": 1694.79
            },
            {
              "x": 780.4,
              "y": 1750.71
            },
            {
              "x": 794.55,
              "y": 1830.22
            },
            {
              "x": 787.13,
              "y": 1865.26
            },
            {
              "x": 806.0,
              "y": 1936.68
            },
            {
              "x": 834.3,
              "y": 1996.65
            },
            {
              "x": 890.22,
              "y": 2028.31
            },
            {
              "x": 942.78,
              "y": 2025.62
            },
            {
              "x": 985.23,
              "y": 2011.47
            },
            {
              "x": 1008.14,
              "y": 1989.23
            },
            {
              "x": 1026.33,
              "y": 1931.96
            },
            {
              "x": 1010.16,
              "y": 1842.35
            },
            {
              "x": 996.01,
              "y": 1812.7
            },
            {
              "x": 925.26,
              "y": 1732.52
            },
            {
              "x": 893.59,
              "y": 1708.94
            },
            {
              "x": 851.82,
              "y": 1665.82
            },
            {
              "x": 828.24,
              "y": 1659.08
            }
          ]
        ]
      },
      "slot_names": [
        "0"
      ]
    },
    {
      "bounding_box": {
        "h": 361.4499999999998,
        "w": 265.2800000000002,
        "x": 2166.24,
        "y": 2499.04
      },
      "id": "3f0f76db-9374-457a-b5e0-66197964394f",
      "name": "GWTE",
      "polygon": {
        "paths": [
          [
            {
              "x": 2189.49,
              "y": 2648.06
            },
            {
              "x": 2208.51,
              "y": 2762.2
            },
            {
              "x": 2264.53,
              "y": 2835.13
            },
            {
              "x": 2318.43,
              "y": 2860.49
            },
            {
              "x": 2363.88,
              "y": 2855.21
            },
            {
              "x": 2398.75,
              "y": 2834.07
            },
            {
              "x": 2399.81,
              "y": 2834.07
            },
            {
              "x": 2431.52,
              "y": 2796.02
            },
            {
              "x": 2431.52,
              "y": 2766.43
            },
            {
              "x": 2418.83,
              "y": 2716.75
            },
            {
              "x": 2409.32,
              "y": 2672.37
            },
            {
              "x": 2354.36,
              "y": 2608.95
            },
            {
              "x": 2322.66,
              "y": 2559.28
            },
            {
              "x": 2222.25,
              "y": 2499.04
            },
            {
              "x": 2211.68,
              "y": 2500.09
            },
            {
              "x": 2200.06,
              "y": 2520.17
            },
            {
              "x": 2205.34,
              "y": 2570.9
            },
            {
              "x": 2186.32,
              "y": 2585.7
            },
            {
              "x": 2173.64,
              "y": 2576.19
            },
            {
              "x": 2166.24,
              "y": 2589.93
            }
          ]
        ]
      },
      "slot_names": [
        "0"
      ]
    },
    {
      "bounding_box": {
        "h": 246.47000000000003,
        "w": 416.9000000000001,
        "x": 1288.32,
        "y": 1551.82
      },
      "id": "4c078f5a-a2d9-4f57-a397-efa7a4bc3f34",
      "name": "GWTE",
      "polygon": {
        "paths": [
          [
            {
              "x": 1397.92,
              "y": 1702.32
            },
            {
              "x": 1452.46,
              "y": 1751.62
            },
            {
              "x": 1482.88,
              "y": 1713.86
            },
            {
              "x": 1485.5,
              "y": 1717.53
            },
            {
              "x": 1480.78,
              "y": 1732.22
            },
            {
              "x": 1461.9,
              "y": 1758.44
            },
            {
              "x": 1492.32,
              "y": 1775.74
            },
            {
              "x": 1521.16,
              "y": 1784.66
            },
            {
              "x": 1559.44,
              "y": 1740.08
            },
            {
              "x": 1577.79,
              "y": 1763.68
            },
            {
              "x": 1590.9,
              "y": 1793.57
            },
            {
              "x": 1584.61,
              "y": 1798.29
            },
            {
              "x": 1570.98,
              "y": 1768.4
            },
            {
              "x": 1559.44,
              "y": 1748.47
            },
            {
              "x": 1529.02,
              "y": 1785.7
            },
            {
              "x": 1591.43,
              "y": 1798.29
            },
            {
              "x": 1640.2,
              "y": 1796.72
            },
            {
              "x": 1675.33,
              "y": 1777.84
            },
            {
              "x": 1694.74,
              "y": 1746.37
            },
            {
              "x": 1704.18,
              "y": 1713.86
            },
            {
              "x": 1705.22,
              "y": 1687.12
            },
            {
              "x": 1690.02,
              "y": 1657.75
            },
            {
              "x": 1683.2,
              "y": 1638.35
            },
            {
              "x": 1666.42,
              "y": 1622.09
            },
            {
              "x": 1644.39,
              "y": 1617.37
            },
            {
              "x": 1639.15,
              "y": 1645.69
            },
            {
              "x": 1631.81,
              "y": 1664.04
            },
            {
              "x": 1607.16,
              "y": 1694.46
            },
            {
              "x": 1593.0,
              "y": 1703.9
            },
            {
              "x": 1577.27,
              "y": 1702.32
            },
            {
              "x": 1576.22,
              "y": 1692.36
            },
            {
              "x": 1597.72,
              "y": 1690.26
            },
            {
              "x": 1624.99,
              "y": 1666.14
            },
            {
              "x": 1637.58,
              "y": 1612.13
            },
            {
              "x": 1610.83,
              "y": 1601.11
            },
            {
              "x": 1491.27,
              "y": 1557.59
            },
            {
              "x": 1469.77,
              "y": 1555.49
            },
            {
              "x": 1463.47,
              "y": 1570.17
            },
            {
              "x": 1370.13,
              "y": 1551.82
            },
            {
              "x": 1324.51,
              "y": 1571.22
            },
            {
              "x": 1312.45,
              "y": 1567.03
            },
            {
              "x": 1315.59,
              "y": 1574.89
            },
            {
              "x": 1307.2,
              "y": 1575.94
            },
            {
              "x": 1317.17,
              "y": 1593.77
            },
            {
              "x": 1311.92,
              "y": 1601.11
            },
            {
              "x": 1331.32,
              "y": 1630.48
            },
            {
              "x": 1359.64,
              "y": 1649.36
            },
            {
              "x": 1321.88,
              "y": 1642.54
            },
            {
              "x": 1288.32,
              "y": 1647.26
            },
            {
              "x": 1288.32,
              "y": 1661.42
            },
            {
              "x": 1368.56,
              "y": 1688.17
            }
          ]
        ]
      },
      "slot_names": [
        "0"
      ]
    },
    {
      "bounding_box": {
        "h": 217.54999999999995,
        "w": 422.4200000000001,
        "x": 2101.86,
        "y": 1084.07
      },
      "id": "036692cf-7c3c-4866-9ecc-9b1790404cf4",
      "name": "GWTE",
      "polygon": {
        "paths": [
          [
            {
              "x": 2104.28,
              "y": 1175.32
            },
            {
              "x": 2147.79,
              "y": 1195.87
            },
            {
              "x": 2193.12,
              "y": 1214.6
            },
            {
              "x": 2164.71,
              "y": 1226.69
            },
            {
              "x": 2149.6,
              "y": 1247.24
            },
            {
              "x": 2171.36,
              "y": 1252.07
            },
            {
              "x": 2189.49,
              "y": 1249.65
            },
            {
              "x": 2202.78,
              "y": 1249.05
            },
            {
              "x": 2173.17,
              "y": 1259.93
            },
            {
              "x": 2156.86,
              "y": 1267.18
            },
            {
              "x": 2179.22,
              "y": 1275.64
            },
            {
              "x": 2205.81,
              "y": 1274.43
            },
            {
              "x": 2212.45,
              "y": 1269.6
            },
            {
              "x": 2243.27,
              "y": 1266.57
            },
            {
              "x": 2290.41,
              "y": 1254.49
            },
            {
              "x": 2291.62,
              "y": 1256.3
            },
            {
              "x": 2268.65,
              "y": 1263.55
            },
            {
              "x": 2275.91,
              "y": 1273.83
            },
            {
              "x": 2342.98,
              "y": 1299.81
            },
            {
              "x": 2394.35,
              "y": 1301.62
            },
            {
              "x": 2462.64,
              "y": 1291.35
            },
            {
              "x": 2500.71,
              "y": 1267.78
            },
            {
              "x": 2520.05,
              "y": 1237.57
            },
            {
              "x": 2524.28,
              "y": 1202.52
            },
            {
              "x": 2505.54,
              "y": 1197.68
            },
            {
              "x": 2474.12,
              "y": 1201.91
            },
            {
              "x": 2491.64,
              "y": 1186.81
            },
            {
              "x": 2522.46,
              "y": 1186.2
            },
            {
              "x": 2520.65,
              "y": 1172.91
            },
            {
              "x": 2503.13,
              "y": 1152.36
            },
            {
              "x": 2490.44,
              "y": 1151.76
            },
            {
              "x": 2494.67,
              "y": 1122.75
            },
            {
              "x": 2485.6,
              "y": 1096.76
            },
            {
              "x": 2448.13,
              "y": 1143.9
            },
            {
              "x": 2446.93,
              "y": 1136.04
            },
            {
              "x": 2460.82,
              "y": 1101.6
            },
            {
              "x": 2472.91,
              "y": 1097.37
            },
            {
              "x": 2468.08,
              "y": 1084.07
            },
            {
              "x": 2401.6,
              "y": 1085.89
            },
            {
              "x": 2388.31,
              "y": 1088.3
            },
            {
              "x": 2387.1,
              "y": 1099.18
            },
            {
              "x": 2380.45,
              "y": 1099.18
            },
            {
              "x": 2380.45,
              "y": 1086.49
            },
            {
              "x": 2316.39,
              "y": 1104.02
            },
            {
              "x": 2258.98,
              "y": 1104.62
            },
            {
              "x": 2207.01,
              "y": 1120.33
            },
            {
              "x": 2181.63,
              "y": 1134.23
            },
            {
              "x": 2162.9,
              "y": 1130.0
            },
            {
              "x": 2162.9,
              "y": 1139.67
            },
            {
              "x": 2156.25,
              "y": 1140.27
            },
            {
              "x": 2152.63,
              "y": 1143.9
            },
            {
              "x": 2133.29,
              "y": 1140.27
            },
            {
              "x": 2124.22,
              "y": 1146.92
            },
            {
              "x": 2110.32,
              "y": 1148.73
            },
            {
              "x": 2101.86,
              "y": 1164.45
            }
          ]
        ]
      },
      "slot_names": [
        "0"
      ]
    },
    {
      "bounding_box": {
        "h": 376.3699999999999,
        "w": 334.3000000000002,
        "x": 2893.35,
        "y": 747.23
      },
      "id": "9200febc-6c99-43fa-a7df-2960d12b5350",
      "name": "GWTE",
      "polygon": {
        "paths": [
          [
            {
              "x": 2916.21,
              "y": 1071.01
            },
            {
              "x": 2939.54,
              "y": 1089.76
            },
            {
              "x": 2968.8,
              "y": 1114.92
            },
            {
              "x": 2996.7,
              "y": 1123.6
            },
            {
              "x": 3001.73,
              "y": 1114.0
            },
            {
              "x": 3018.65,
              "y": 1115.83
            },
            {
              "x": 3037.86,
              "y": 1103.94
            },
            {
              "x": 3054.32,
              "y": 1105.77
            },
            {
              "x": 3087.25,
              "y": 1089.31
            },
            {
              "x": 3071.24,
              "y": 1076.96
            },
            {
              "x": 3061.18,
              "y": 1076.5
            },
            {
              "x": 3009.96,
              "y": 1035.8
            },
            {
              "x": 2931.76,
              "y": 1025.28
            },
            {
              "x": 2893.35,
              "y": 1028.02
            },
            {
              "x": 2893.35,
              "y": 1017.96
            },
            {
              "x": 2917.13,
              "y": 1016.13
            },
            {
              "x": 3001.27,
              "y": 1028.48
            },
            {
              "x": 2994.87,
              "y": 1020.25
            },
            {
              "x": 2963.32,
              "y": 1000.13
            },
            {
              "x": 2947.31,
              "y": 991.44
            },
            {
              "x": 2911.18,
              "y": 991.9
            },
            {
              "x": 2906.15,
              "y": 1004.7
            },
            {
              "x": 2902.49,
              "y": 1005.16
            },
            {
              "x": 2910.72,
              "y": 975.43
            },
            {
              "x": 2913.47,
              "y": 977.72
            },
            {
              "x": 2925.82,
              "y": 966.74
            },
            {
              "x": 2929.02,
              "y": 969.03
            },
            {
              "x": 2918.96,
              "y": 980.92
            },
            {
              "x": 2945.48,
              "y": 984.58
            },
            {
              "x": 3032.37,
              "y": 985.95
            },
            {
              "x": 3040.15,
              "y": 977.26
            },
            {
              "x": 3042.43,
              "y": 981.38
            },
            {
              "x": 3040.15,
              "y": 985.49
            },
            {
              "x": 3154.02,
              "y": 989.15
            },
            {
              "x": 3079.93,
              "y": 944.33
            },
            {
              "x": 3052.95,
              "y": 939.76
            },
            {
              "x": 3048.38,
              "y": 934.73
            },
            {
              "x": 3025.51,
              "y": 929.7
            },
            {
              "x": 3005.39,
              "y": 921.01
            },
            {
              "x": 2998.53,
              "y": 921.01
            },
            {
              "x": 2991.67,
              "y": 915.98
            },
            {
              "x": 2953.71,
              "y": 906.38
            },
            {
              "x": 2958.29,
              "y": 898.6
            },
            {
              "x": 3064.38,
              "y": 931.07
            },
            {
              "x": 3095.48,
              "y": 944.79
            },
            {
              "x": 3134.35,
              "y": 969.03
            },
            {
              "x": 3157.68,
              "y": 941.13
            },
            {
              "x": 3175.51,
              "y": 927.41
            },
            {
              "x": 3178.26,
              "y": 911.86
            },
            {
              "x": 3187.86,
              "y": 915.07
            },
            {
              "x": 3185.12,
              "y": 926.04
            },
            {
              "x": 3143.5,
              "y": 970.86
            },
            {
              "x": 3143.96,
              "y": 974.06
            },
            {
              "x": 3158.14,
              "y": 962.17
            },
            {
              "x": 3159.96,
              "y": 971.32
            },
            {
              "x": 3158.14,
              "y": 986.41
            },
            {
              "x": 3154.48,
              "y": 996.47
            },
            {
              "x": 3104.63,
              "y": 996.47
            },
            {
              "x": 3020.48,
              "y": 994.18
            },
            {
              "x": 2969.26,
              "y": 991.9
            },
            {
              "x": 3014.99,
              "y": 1029.4
            },
            {
              "x": 3057.52,
              "y": 1039.46
            },
            {
              "x": 3057.98,
              "y": 1029.85
            },
            {
              "x": 3065.3,
              "y": 1031.23
            },
            {
              "x": 3070.79,
              "y": 1042.66
            },
            {
              "x": 3123.38,
              "y": 1056.84
            },
            {
              "x": 3115.15,
              "y": 1062.32
            },
            {
              "x": 3071.7,
              "y": 1046.77
            },
            {
              "x": 3030.54,
              "y": 1039.46
            },
            {
              "x": 3062.1,
              "y": 1067.81
            },
            {
              "x": 3072.62,
              "y": 1067.81
            },
            {
              "x": 3090.45,
              "y": 1082.45
            },
            {
              "x": 3114.23,
              "y": 1065.52
            },
            {
              "x": 3127.95,
              "y": 1048.15
            },
            {
              "x": 3136.64,
              "y": 1044.03
            },
            {
              "x": 3136.18,
              "y": 1039.0
            },
            {
              "x": 3140.76,
              "y": 1032.6
            },
            {
              "x": 3153.11,
              "y": 999.67
            },
            {
              "x": 3160.88,
              "y": 969.49
            },
            {
              "x": 3170.48,
              "y": 941.13
            },
            {
              "x": 3188.32,
              "y": 922.84
            },
            {
              "x": 3227.65,
              "y": 862.93
            },
            {
              "x": 3190.61,
              "y": 859.27
            },
            {
              "x": 3188.78,
              "y": 851.04
            },
            {
              "x": 3197.92,
              "y": 850.13
            },
            {
              "x": 3203.41,
              "y": 828.63
            },
            {
              "x": 3199.29,
              "y": 794.79
            },
            {
              "x": 3192.43,
              "y": 805.31
            },
            {
              "x": 3187.86,
              "y": 776.04
            },
            {
              "x": 3177.8,
              "y": 759.58
            },
            {
              "x": 3143.96,
              "y": 779.24
            },
            {
              "x": 3142.59,
              "y": 771.01
            },
            {
              "x": 3132.53,
              "y": 771.01
            },
            {
              "x": 3133.44,
              "y": 759.58
            },
            {
              "x": 3127.04,
              "y": 747.23
            },
            {
              "x": 3120.18,
              "y": 753.17
            },
            {
              "x": 3099.6,
              "y": 792.5
            },
            {
              "x": 3080.85,
              "y": 790.22
            },
            {
              "x": 3058.44,
              "y": 823.14
            },
            {
              "x": 3008.13,
              "y": 855.61
            },
            {
              "x": 2961.94,
              "y": 892.66
            },
            {
              "x": 2937.25,
              "y": 925.58
            },
            {
              "x": 2908.89,
              "y": 974.97
            },
            {
              "x": 2901.58,
              "y": 1007.9
            },
            {
              "x": 2893.35,
              "y": 1017.51
            },
            {
              "x": 2895.18,
              "y": 1034.88
            }
          ]
        ]
      },
      "slot_names": [
        "0"
      ]
    },
    {
      "bounding_box": {
        "h": 434.3599999999999,
        "w": 454.0100000000002,
        "x": 3467.39,
        "y": 1056.51
      },
      "id": "daa939f6-ac29-454e-9ddb-d0c747f3efab",
      "name": "MALL",
      "polygon": {
        "paths": [
          [
            {
              "x": 3467.39,
              "y": 1063.53
            },
            {
              "x": 3474.41,
              "y": 1197.55
            },
            {
              "x": 3475.11,
              "y": 1197.55
            },
            {
              "x": 3510.9,
              "y": 1294.39
            },
            {
              "x": 3593.7,
              "y": 1393.33
            },
            {
              "x": 3720.01,
              "y": 1465.61
            },
            {
              "x": 3785.97,
              "y": 1490.87
            },
            {
              "x": 3845.62,
              "y": 1488.77
            },
            {
              "x": 3899.65,
              "y": 1439.65
            },
            {
              "x": 3921.4,
              "y": 1375.79
            },
            {
              "x": 3913.69,
              "y": 1317.55
            },
            {
              "x": 3800.71,
              "y": 1140.01
            },
            {
              "x": 3704.57,
              "y": 1087.39
            },
            {
              "x": 3618.96,
              "y": 1056.51
            },
            {
              "x": 3488.44,
              "y": 1056.51
            }
          ]
        ]
      },
      "slot_names": [
        "0"
      ]
    },
    {
      "bounding_box": {
        "h": 282.4500000000003,
        "w": 279.6100000000001,
        "x": 2908.5,
        "y": 2026.12
      },
      "id": "edc0b064-dd97-43d0-9974-1c5c5300e93d",
      "name": "Hen",
      "polygon": {
        "paths": [
          [
            {
              "x": 2948.31,
              "y": 2198.62
            },
            {
              "x": 2954.95,
              "y": 2200.99
            },
            {
              "x": 2960.16,
              "y": 2218.53
            },
            {
              "x": 2988.12,
              "y": 2254.07
            },
            {
              "x": 3034.09,
              "y": 2291.03
            },
            {
              "x": 3084.33,
              "y": 2308.57
            },
            {
              "x": 3117.97,
              "y": 2293.88
            },
            {
              "x": 3151.62,
              "y": 2273.97
            },
            {
              "x": 3153.04,
              "y": 2259.76
            },
            {
              "x": 3162.05,
              "y": 2227.53
            },
            {
              "x": 3161.1,
              "y": 2195.3
            },
            {
              "x": 3163.0,
              "y": 2184.4
            },
            {
              "x": 3161.1,
              "y": 2145.07
            },
            {
              "x": 3167.73,
              "y": 2149.81
            },
            {
              "x": 3168.68,
              "y": 2189.62
            },
            {
              "x": 3166.31,
              "y": 2219.95
            },
            {
              "x": 3157.78,
              "y": 2271.6
            },
            {
              "x": 3180.06,
              "y": 2251.22
            },
            {
              "x": 3188.11,
              "y": 2213.79
            },
            {
              "x": 3178.63,
              "y": 2170.19
            },
            {
              "x": 3170.1,
              "y": 2147.91
            },
            {
              "x": 3147.36,
              "y": 2128.96
            },
            {
              "x": 3118.45,
              "y": 2113.32
            },
            {
              "x": 3110.39,
              "y": 2101.0
            },
            {
              "x": 3073.43,
              "y": 2116.16
            },
            {
              "x": 3078.17,
              "y": 2107.63
            },
            {
              "x": 3094.28,
              "y": 2100.05
            },
            {
              "x": 3099.96,
              "y": 2084.88
            },
            {
              "x": 3057.79,
              "y": 2040.33
            },
            {
              "x": 3073.43,
              "y": 2107.16
            },
            {
              "x": 3070.58,
              "y": 2108.1
            },
            {
              "x": 3058.26,
              "y": 2083.46
            },
            {
              "x": 3046.41,
              "y": 2047.44
            },
            {
              "x": 3000.44,
              "y": 2121.85
            },
            {
              "x": 3007.08,
              "y": 2148.86
            },
            {
              "x": 3005.66,
              "y": 2167.82
            },
            {
              "x": 3000.92,
              "y": 2166.87
            },
            {
              "x": 3001.39,
              "y": 2155.02
            },
            {
              "x": 2994.76,
              "y": 2128.96
            },
            {
              "x": 2951.63,
              "y": 2191.51
            },
            {
              "x": 2947.84,
              "y": 2196.25
            },
            {
              "x": 2943.1,
              "y": 2189.14
            },
            {
              "x": 2965.85,
              "y": 2161.18
            },
            {
              "x": 2990.49,
              "y": 2125.16
            },
            {
              "x": 3016.56,
              "y": 2076.35
            },
            {
              "x": 3010.4,
              "y": 2074.93
            },
            {
              "x": 3003.29,
              "y": 2076.83
            },
            {
              "x": 2995.23,
              "y": 2093.41
            },
            {
              "x": 2998.07,
              "y": 2110.47
            },
            {
              "x": 2991.44,
              "y": 2121.85
            },
            {
              "x": 2982.43,
              "y": 2101.47
            },
            {
              "x": 2973.43,
              "y": 2116.16
            },
            {
              "x": 2968.69,
              "y": 2118.53
            },
            {
              "x": 2963.0,
              "y": 2129.9
            },
            {
              "x": 2946.89,
              "y": 2138.43
            },
            {
              "x": 2932.2,
              "y": 2147.44
            },
            {
              "x": 2931.73,
              "y": 2128.01
            },
            {
              "x": 2949.74,
              "y": 2117.11
            },
            {
              "x": 2959.21,
              "y": 2100.52
            },
            {
              "x": 2975.8,
              "y": 2088.2
            },
            {
              "x": 3036.93,
              "y": 2028.49
            },
            {
              "x": 3031.25,
              "y": 2028.49
            },
            {
              "x": 3024.61,
              "y": 2041.76
            },
            {
              "x": 3012.29,
              "y": 2044.6
            },
            {
              "x": 3020.82,
              "y": 2030.86
            },
            {
              "x": 2982.43,
              "y": 2026.12
            },
            {
              "x": 2975.8,
              "y": 2027.54
            },
            {
              "x": 2988.12,
              "y": 2076.35
            },
            {
              "x": 2977.22,
              "y": 2084.88
            },
            {
              "x": 2969.17,
              "y": 2034.65
            },
            {
              "x": 2955.9,
              "y": 2050.76
            },
            {
              "x": 2965.85,
              "y": 2056.45
            },
            {
              "x": 2970.59,
              "y": 2052.66
            },
            {
              "x": 2973.43,
              "y": 2067.35
            },
            {
              "x": 2959.21,
              "y": 2062.61
            },
            {
              "x": 2961.11,
              "y": 2070.19
            },
            {
              "x": 2957.79,
              "y": 2074.46
            },
            {
              "x": 2952.1,
              "y": 2061.19
            },
            {
              "x": 2943.57,
              "y": 2079.67
            },
            {
              "x": 2945.47,
              "y": 2095.31
            },
            {
              "x": 2939.31,
              "y": 2085.36
            },
            {
              "x": 2930.78,
              "y": 2104.31
            },
            {
              "x": 2927.46,
              "y": 2098.63
            },
            {
              "x": 2944.05,
              "y": 2062.61
            },
            {
              "x": 2960.64,
              "y": 2035.6
            },
            {
              "x": 2927.46,
              "y": 2028.96
            },
            {
              "x": 2908.5,
              "y": 2039.39
            },
            {
              "x": 2917.51,
              "y": 2063.08
            },
            {
              "x": 2917.51,
              "y": 2076.35
            },
            {
              "x": 2932.67,
              "y": 2113.79
            },
            {
              "x": 2931.25,
              "y": 2138.91
            },
            {
              "x": 2934.57,
              "y": 2158.34
            },
            {
              "x": 2941.68,
              "y": 2165.92
            },
            {
              "x": 2938.36,
              "y": 2171.61
            },
            {
              "x": 2944.05,
              "y": 2188.67
            }
          ]
        ]
      },
      "slot_names": [
        "0"
      ]
    },
    {
      "bounding_box": {
        "h": 289.02,
        "w": 362.3399999999999,
        "x": 1574.26,
        "y": 2084.5
      },
      "id": "be7f42e9-ec6c-4665-824d-8bb29c476dac",
      "name": "Hen",
      "polygon": {
        "paths": [
          [
            {
              "x": 1600.6,
              "y": 2326.54
            },
            {
              "x": 1637.62,
              "y": 2364.27
            },
            {
              "x": 1673.21,
              "y": 2372.81
            },
            {
              "x": 1697.41,
              "y": 2373.52
            },
            {
              "x": 1736.57,
              "y": 2363.55
            },
            {
              "x": 1781.41,
              "y": 2344.33
            },
            {
              "x": 1834.09,
              "y": 2304.47
            },
            {
              "x": 1872.53,
              "y": 2257.49
            },
            {
              "x": 1870.4,
              "y": 2250.37
            },
            {
              "x": 1912.4,
              "y": 2228.3
            },
            {
              "x": 1924.5,
              "y": 2179.18
            },
            {
              "x": 1936.6,
              "y": 2149.99
            },
            {
              "x": 1918.81,
              "y": 2127.92
            },
            {
              "x": 1928.77,
              "y": 2084.5
            },
            {
              "x": 1862.57,
              "y": 2092.33
            },
            {
              "x": 1797.08,
              "y": 2110.13
            },
            {
              "x": 1708.09,
              "y": 2150.7
            },
            {
              "x": 1636.9,
              "y": 2186.3
            },
            {
              "x": 1586.36,
              "y": 2245.38
            },
            {
              "x": 1574.26,
              "y": 2278.84
            }
          ]
        ]
      },
      "slot_names": [
        "0"
      ]
    },
    {
      "bounding_box": {
        "h": 270.8799999999999,
        "w": 387.6199999999999,
        "x": 2357.0,
        "y": 1805.91
      },
      "id": "759452c3-079d-4d70-a9f9-653c5c568861",
      "name": "GWTE",
      "polygon": {
        "paths": [
          [
            {
              "x": 2357.0,
              "y": 2007.77
            },
            {
              "x": 2369.66,
              "y": 2027.9
            },
            {
              "x": 2398.99,
              "y": 2031.93
            },
            {
              "x": 2399.56,
              "y": 2040.55
            },
            {
              "x": 2449.6,
              "y": 2045.73
            },
            {
              "x": 2439.24,
              "y": 2051.48
            },
            {
              "x": 2436.94,
              "y": 2064.13
            },
            {
              "x": 2441.54,
              "y": 2063.56
            },
            {
              "x": 2445.57,
              "y": 2057.81
            },
            {
              "x": 2463.4,
              "y": 2050.33
            },
            {
              "x": 2446.72,
              "y": 2066.43
            },
            {
              "x": 2446.72,
              "y": 2074.48
            },
            {
              "x": 2452.47,
              "y": 2076.79
            },
            {
              "x": 2472.6,
              "y": 2061.26
            },
            {
              "x": 2545.06,
              "y": 2051.48
            },
            {
              "x": 2584.74,
              "y": 2042.85
            },
            {
              "x": 2599.7,
              "y": 2042.85
            },
            {
              "x": 2645.13,
              "y": 2028.48
            },
            {
              "x": 2694.01,
              "y": 2000.87
            },
            {
              "x": 2733.12,
              "y": 1964.64
            },
            {
              "x": 2744.62,
              "y": 1928.98
            },
            {
              "x": 2736.57,
              "y": 1885.28
            },
            {
              "x": 2725.65,
              "y": 1881.25
            },
            {
              "x": 2711.27,
              "y": 1930.71
            },
            {
              "x": 2707.24,
              "y": 1952.56
            },
            {
              "x": 2706.67,
              "y": 1930.71
            },
            {
              "x": 2717.02,
              "y": 1882.97
            },
            {
              "x": 2594.52,
              "y": 1882.4
            },
            {
              "x": 2491.58,
              "y": 1887.0
            },
            {
              "x": 2450.17,
              "y": 1887.0
            },
            {
              "x": 2481.8,
              "y": 1878.95
            },
            {
              "x": 2633.63,
              "y": 1872.62
            },
            {
              "x": 2674.46,
              "y": 1873.77
            },
            {
              "x": 2700.34,
              "y": 1864.57
            },
            {
              "x": 2709.54,
              "y": 1843.29
            },
            {
              "x": 2708.39,
              "y": 1833.52
            },
            {
              "x": 2688.26,
              "y": 1827.19
            },
            {
              "x": 2668.71,
              "y": 1832.37
            },
            {
              "x": 2615.23,
              "y": 1835.82
            },
            {
              "x": 2618.1,
              "y": 1871.47
            },
            {
              "x": 2608.9,
              "y": 1872.05
            },
            {
              "x": 2607.75,
              "y": 1835.24
            },
            {
              "x": 2551.96,
              "y": 1836.97
            },
            {
              "x": 2532.41,
              "y": 1840.99
            },
            {
              "x": 2526.66,
              "y": 1861.7
            },
            {
              "x": 2526.66,
              "y": 1845.59
            },
            {
              "x": 2503.08,
              "y": 1845.59
            },
            {
              "x": 2514.01,
              "y": 1831.79
            },
            {
              "x": 2524.36,
              "y": 1834.09
            },
            {
              "x": 2528.38,
              "y": 1831.22
            },
            {
              "x": 2530.69,
              "y": 1819.71
            },
            {
              "x": 2539.31,
              "y": 1817.99
            },
            {
              "x": 2537.59,
              "y": 1828.34
            },
            {
              "x": 2607.75,
              "y": 1827.19
            },
            {
              "x": 2606.6,
              "y": 1817.99
            },
            {
              "x": 2615.23,
              "y": 1815.11
            },
            {
              "x": 2615.23,
              "y": 1822.59
            },
            {
              "x": 2653.18,
              "y": 1824.31
            },
            {
              "x": 2679.64,
              "y": 1821.44
            },
            {
              "x": 2651.46,
              "y": 1805.91
            },
            {
              "x": 2598.55,
              "y": 1815.69
            },
            {
              "x": 2527.81,
              "y": 1819.71
            },
            {
              "x": 2502.5,
              "y": 1846.74
            },
            {
              "x": 2524.93,
              "y": 1847.89
            },
            {
              "x": 2474.9,
              "y": 1873.77
            },
            {
              "x": 2477.2,
              "y": 1878.95
            },
            {
              "x": 2447.87,
              "y": 1888.73
            },
            {
              "x": 2373.68,
              "y": 1938.76
            },
            {
              "x": 2379.43,
              "y": 1947.39
            },
            {
              "x": 2456.5,
              "y": 1910.58
            },
            {
              "x": 2371.96,
              "y": 1977.29
            },
            {
              "x": 2362.75,
              "y": 1991.67
            }
          ]
        ]
      },
      "slot_names": [
        "0"
      ]
    }
  ]
}