{
  "version": "2.0",
  "schema_ref": "https://darwin-public.s3.eu-west-1.amazonaws.com/darwin_json/2.0/schema.json",
  "item": {
    "name": "DJI_20230105093816_0112_Z.JPG",
    "path": "/",
    "source_info": {
      "dataset": {
        "name": "Winter 22 - Zoom Camera Images",
        "slug": "winter-22-zoom-camera-images",
        "dataset_management_url": "https://darwin.v7labs.com/datasets/614552/dataset-management"
      },
      "item_id": "018624b7-57f3-2c99-664c-ba7f9815c91f",
      "team": {
        "name": "MAV Dronework",
        "slug": "mav-dronework"
      },
      "workview_url": "https://darwin.v7labs.com/workview?dataset=614552&item=018624b7-57f3-2c99-664c-ba7f9815c91f"
    },
    "slots": [
      {
        "type": "image",
        "slot_name": "0",
        "width": 5184,
        "height": 2916,
        "thumbnail_url": "https://darwin.v7labs.com/api/v2/teams/mav-dronework/files/6a039515-cbc0-4e8a-b299-5dc9fc9b0797/thumbnail",
        "source_files": [
          {
            "file_name": "DJI_20230105093816_0112_Z.JPG",
            "url": "https://darwin.v7labs.com/api/v2/teams/mav-dronework/uploads/e615c4d4-de21-40a6-8214-3a2b7f8ecfa9"
          }
        ]
      }
    ]
  },
  "annotations": [
    {
      "bounding_box": {
        "h": 376.1400000000001,
        "w": 387.39,
        "x": 413.35,
        "y": 1498.99
      },
      "id": "101c3150-8cb1-41c1-991b-cee46f33408e",
      "name": "Hen",
      "polygon": {
        "paths": [
          [
            {
              "x": 502.28,
              "y": 1504.1
            },
            {
              "x": 520.68,
              "y": 1510.24
            },
            {
              "x": 555.43,
              "y": 1543.97
            },
            {
              "x": 647.42,
              "y": 1578.72
            },
            {
              "x": 688.3,
              "y": 1603.25
            },
            {
              "x": 730.21,
              "y": 1645.16
            },
            {
              "x": 745.54,
              "y": 1664.58
            },
            {
              "x": 752.7,
              "y": 1688.09
            },
            {
              "x": 771.1,
              "y": 1706.48
            },
            {
              "x": 771.1,
              "y": 1714.66
            },
            {
              "x": 783.36,
              "y": 1728.97
            },
            {
              "x": 777.23,
              "y": 1737.15
            },
            {
              "x": 783.36,
              "y": 1760.66
            },
            {
              "x": 791.54,
              "y": 1765.77
            },
            {
              "x": 785.41,
              "y": 1785.19
            },
            {
              "x": 794.6,
              "y": 1800.52
            },
            {
              "x": 800.74,
              "y": 1830.16
            },
            {
              "x": 778.25,
              "y": 1853.67
            },
            {
              "x": 748.61,
              "y": 1856.73
            },
            {
              "x": 687.28,
              "y": 1875.13
            },
            {
              "x": 604.49,
              "y": 1847.54
            },
            {
              "x": 532.94,
              "y": 1788.25
            },
            {
              "x": 490.01,
              "y": 1716.7
            },
            {
              "x": 483.88,
              "y": 1695.24
            },
            {
              "x": 457.31,
              "y": 1689.11
            },
            {
              "x": 429.71,
              "y": 1697.28
            },
            {
              "x": 413.35,
              "y": 1682.97
            },
            {
              "x": 420.51,
              "y": 1644.13
            },
            {
              "x": 455.26,
              "y": 1654.36
            },
            {
              "x": 482.86,
              "y": 1665.6
            },
            {
              "x": 484.9,
              "y": 1651.29
            },
            {
              "x": 469.57,
              "y": 1616.54
            },
            {
              "x": 444.02,
              "y": 1542.94
            },
            {
              "x": 444.02,
              "y": 1529.66
            },
            {
              "x": 456.28,
              "y": 1529.66
            },
            {
              "x": 461.39,
              "y": 1517.39
            },
            {
              "x": 464.46,
              "y": 1515.35
            },
            {
              "x": 464.46,
              "y": 1498.99
            },
            {
              "x": 486.95,
              "y": 1505.13
            },
            {
              "x": 499.21,
              "y": 1522.5
            },
            {
              "x": 495.12,
              "y": 1511.26
            }
          ]
        ]
      },
      "slot_names": [
        "0"
      ]
    },
    {
      "bounding_box": {
        "h": 251.11000000000013,
        "w": 564.99,
        "x": 1995.28,
        "y": 2094.04
      },
      "id": "5d36aada-a2e3-4b71-aab3-85c10510ff7b",
      "name": "REDH",
      "polygon": {
        "paths": [
          [
            {
              "x": 1995.28,
              "y": 2232.95
            },
            {
              "x": 2100.8,
              "y": 2289.05
            },
            {
              "x": 2138.2,
              "y": 2298.4
            },
            {
              "x": 2213.0,
              "y": 2329.12
            },
            {
              "x": 2335.88,
              "y": 2345.15
            },
            {
              "x": 2418.69,
              "y": 2322.44
            },
            {
              "x": 2492.16,
              "y": 2278.36
            },
            {
              "x": 2513.53,
              "y": 2240.96
            },
            {
              "x": 2517.53,
              "y": 2215.59
            },
            {
              "x": 2509.52,
              "y": 2182.2
            },
            {
              "x": 2537.57,
              "y": 2194.22
            },
            {
              "x": 2560.27,
              "y": 2178.19
            },
            {
              "x": 2560.27,
              "y": 2152.81
            },
            {
              "x": 2540.24,
              "y": 2128.77
            },
            {
              "x": 2521.54,
              "y": 2140.79
            },
            {
              "x": 2489.48,
              "y": 2146.13
            },
            {
              "x": 2461.44,
              "y": 2116.75
            },
            {
              "x": 2404.0,
              "y": 2111.4
            },
            {
              "x": 2347.9,
              "y": 2094.04
            },
            {
              "x": 2305.16,
              "y": 2099.38
            },
            {
              "x": 2267.76,
              "y": 2095.38
            },
            {
              "x": 2226.36,
              "y": 2096.71
            },
            {
              "x": 2177.36,
              "y": 2113.68
            },
            {
              "x": 2122.17,
              "y": 2151.47
            },
            {
              "x": 2064.74,
              "y": 2183.53
            },
            {
              "x": 2047.38,
              "y": 2187.54
            },
            {
              "x": 2011.31,
              "y": 2194.22
            },
            {
              "x": 2003.3,
              "y": 2199.56
            },
            {
              "x": 1996.62,
              "y": 2207.57
            },
            {
              "x": 1995.28,
              "y": 2207.57
            }
          ]
        ]
      },
      "slot_names": [
        "0"
      ]
    },
    {
      "bounding_box": {
        "h": 431.7099999999998,
        "w": 337.90999999999985,
        "x": 4766.58,
        "y": 1944.93
      },
      "id": "a08dd853-321c-468f-89e7-9a8d26405003",
      "name": "Hen",
      "polygon": {
        "paths": [
          [
            {
              "x": 4807.51,
              "y": 2061.79
            },
            {
              "x": 4784.44,
              "y": 2007.46
            },
            {
              "x": 4788.16,
              "y": 1982.89
            },
            {
              "x": 4811.24,
              "y": 1988.85
            },
            {
              "x": 4800.07,
              "y": 1966.52
            },
            {
              "x": 4835.8,
              "y": 1958.33
            },
            {
              "x": 4826.87,
              "y": 1945.68
            },
            {
              "x": 4850.68,
              "y": 1956.84
            },
            {
              "x": 4862.59,
              "y": 1944.93
            },
            {
              "x": 4875.25,
              "y": 1959.08
            },
            {
              "x": 4883.43,
              "y": 1962.05
            },
            {
              "x": 4895.34,
              "y": 1980.66
            },
            {
              "x": 4899.06,
              "y": 1997.04
            },
            {
              "x": 4909.48,
              "y": 2002.25
            },
            {
              "x": 4912.46,
              "y": 2011.18
            },
            {
              "x": 5009.22,
              "y": 2072.96
            },
            {
              "x": 5043.46,
              "y": 2107.19
            },
            {
              "x": 5045.69,
              "y": 2119.1
            },
            {
              "x": 5062.07,
              "y": 2133.25
            },
            {
              "x": 5090.35,
              "y": 2200.23
            },
            {
              "x": 5100.03,
              "y": 2278.39
            },
            {
              "x": 5097.8,
              "y": 2316.35
            },
            {
              "x": 5104.49,
              "y": 2331.98
            },
            {
              "x": 5093.33,
              "y": 2346.12
            },
            {
              "x": 5066.53,
              "y": 2346.12
            },
            {
              "x": 5021.13,
              "y": 2370.68
            },
            {
              "x": 4966.05,
              "y": 2376.64
            },
            {
              "x": 4908.74,
              "y": 2358.03
            },
            {
              "x": 4859.62,
              "y": 2292.53
            },
            {
              "x": 4818.68,
              "y": 2229.26
            },
            {
              "x": 4813.47,
              "y": 2177.9
            },
            {
              "x": 4774.02,
              "y": 2168.97
            },
            {
              "x": 4766.58,
              "y": 2157.06
            },
            {
              "x": 4775.51,
              "y": 2138.46
            },
            {
              "x": 4800.07,
              "y": 2150.36
            },
            {
              "x": 4814.21,
              "y": 2148.13
            },
            {
              "x": 4810.49,
              "y": 2096.77
            },
            {
              "x": 4802.3,
              "y": 2067.75
            }
          ]
        ]
      },
      "slot_names": [
        "0"
      ]
    },
    {
      "bounding_box": {
        "h": 391.29999999999995,
        "w": 291.22999999999956,
        "x": 4464.09,
        "y": 1077.19
      },
      "id": "758ca758-93bc-480b-8b16-d5987c82e8ae",
      "name": "Hen",
      "polygon": {
        "paths": [
          [
            {
              "x": 4636.07,
              "y": 1468.49
            },
            {
              "x": 4646.26,
              "y": 1450.51
            },
            {
              "x": 4641.46,
              "y": 1431.93
            },
            {
              "x": 4646.86,
              "y": 1420.55
            },
            {
              "x": 4649.25,
              "y": 1386.39
            },
            {
              "x": 4659.44,
              "y": 1377.4
            },
            {
              "x": 4672.03,
              "y": 1375.01
            },
            {
              "x": 4658.24,
              "y": 1394.78
            },
            {
              "x": 4672.62,
              "y": 1395.38
            },
            {
              "x": 4704.38,
              "y": 1372.01
            },
            {
              "x": 4712.77,
              "y": 1354.03
            },
            {
              "x": 4732.55,
              "y": 1318.68
            },
            {
              "x": 4743.33,
              "y": 1292.91
            },
            {
              "x": 4750.52,
              "y": 1237.18
            },
            {
              "x": 4751.72,
              "y": 1194.64
            },
            {
              "x": 4755.32,
              "y": 1177.86
            },
            {
              "x": 4743.93,
              "y": 1134.12
            },
            {
              "x": 4725.36,
              "y": 1099.36
            },
            {
              "x": 4710.38,
              "y": 1098.16
            },
            {
              "x": 4710.38,
              "y": 1097.56
            },
            {
              "x": 4671.43,
              "y": 1090.37
            },
            {
              "x": 4647.46,
              "y": 1077.19
            },
            {
              "x": 4613.3,
              "y": 1080.78
            },
            {
              "x": 4586.34,
              "y": 1092.17
            },
            {
              "x": 4570.16,
              "y": 1109.55
            },
            {
              "x": 4518.62,
              "y": 1128.12
            },
            {
              "x": 4492.86,
              "y": 1140.71
            },
            {
              "x": 4464.09,
              "y": 1138.91
            },
            {
              "x": 4465.89,
              "y": 1235.99
            },
            {
              "x": 4483.27,
              "y": 1259.95
            },
            {
              "x": 4501.24,
              "y": 1267.74
            },
            {
              "x": 4488.06,
              "y": 1278.53
            },
            {
              "x": 4483.27,
              "y": 1317.48
            },
            {
              "x": 4524.61,
              "y": 1357.63
            },
            {
              "x": 4573.15,
              "y": 1379.2
            },
            {
              "x": 4593.53,
              "y": 1381.0
            },
            {
              "x": 4593.53,
              "y": 1381.6
            },
            {
              "x": 4595.92,
              "y": 1373.81
            },
            {
              "x": 4600.12,
              "y": 1393.58
            },
            {
              "x": 4616.9,
              "y": 1413.96
            },
            {
              "x": 4622.29,
              "y": 1461.3
            }
          ]
        ]
      },
      "slot_names": [
        "0"
      ]
    }
  ]
}